{"cameraMode":{"drawMode":0,"name":"Shaded","section":"Shading Mode"},"sceneLighting":true,"audioPlay":false,"sceneViewState":{"m_AlwaysRefresh":false,"showFog":true,"showSkybox":true,"showFlares":true,"showImageEffects":true,"showParticleSystems":true,"showVisualEffectGraphs":true,"m_FxEnabled":true},"in2DMode":false,"pivot":{"x":8.659383773803711,"y":1.3347325325012208,"z":-0.5968676209449768},"rotation":{"x":0.09284163266420365,"y":0.8503491282463074,"z":-0.16028711199760438,"w":0.4925404191017151},"size":2.2234625816345217,"orthographic":false}